pyglotaran/__init__.py
pyglotaran_alias-0.0.5.dist-info/LICENSE
pyglotaran_alias-0.0.5.dist-info/METADATA
pyglotaran_alias-0.0.5.dist-info/WHEEL
pyglotaran_alias-0.0.5.dist-info/entry_points.txt
pyglotaran_alias-0.0.5.dist-info/top_level.txt
pyglotaran_alias-0.0.5.dist-info/RECORD
