Metadata-Version: 2.1
Name: pyglotaran-alias
Version: 0.0.5
Summary: Convenience module, which allows to use pyglotaran as alias in the CLI and imports
Home-page: https://github.com/glotaran/pyglotaran-alias
Author: Sebastian Weigand
Author-email: s.weigand.phy@gmail.com
License: Apache-2.0
Project-URL: Core-Project, https://github.com/glotaran/pyglotaran
Project-URL: Source, https://github.com/glotaran/pyglotaran-alias
Project-URL: Tracker, https://github.com/glotaran/pyglotaran-alias/issues
Platform: UNKNOWN
Classifier: Development Status :: 4 - Beta
Classifier: License :: OSI Approved :: Apache Software License
Classifier: Programming Language :: Python :: 3
Classifier: Programming Language :: Python :: 3 :: Only
Classifier: Programming Language :: Python :: 3.8
Classifier: Programming Language :: Python :: Implementation :: CPython
Classifier: Topic :: Scientific/Engineering
Classifier: Topic :: Scientific/Engineering :: Chemistry
Classifier: Topic :: Scientific/Engineering :: Physics
Requires-Python: >=3.8
